Metadata-Version: 2.1
Name: afwizard-library
Version: 0.0.9
Summary: Community-contributed filter pipelines for AFWizard
Home-page: UNKNOWN
Author: Dominic Kempf
Author-email: ssc@iwr.uni-heidelberg.de
License: MIT
Platform: UNKNOWN
Classifier: License :: OSI Approved :: MIT License
Classifier: Operating System :: OS Independent
Classifier: Programming Language :: Python :: 3
License-File: LICENSE.md
